README.txt
setup.py
isotoma/__init__.py
isotoma.recipe.distros.egg-info/PKG-INFO
isotoma.recipe.distros.egg-info/SOURCES.txt
isotoma.recipe.distros.egg-info/dependency_links.txt
isotoma.recipe.distros.egg-info/entry_points.txt
isotoma.recipe.distros.egg-info/namespace_packages.txt
isotoma.recipe.distros.egg-info/requires.txt
isotoma.recipe.distros.egg-info/top_level.txt
isotoma/recipe/__init__.py
isotoma/recipe/distros/__init__.py