Metadata-Version: 1.0
Name: isotoma.recipe.distros
Version: 0.0.0
Summary: Recipe to install old style products.
Home-page: http://pypi.python.org/pypi/plone.recipe.distros
Author: John Carr
Author-email: john.carr@isotoma.com
License: ZPL 2.1
Keywords: buildout
Platform: UNKNOWN
Classifier: License :: OSI Approved :: Zope Public License
Classifier: Framework :: Plone
Classifier: Framework :: Buildout
Classifier: Programming Language :: Python
